{
  "context": {
    "domain": "ONDC:NTS10",
    "location": {
      "country": {
        "code": "IND"
      },
      "city": {
        "code": "*"
      }
    },
    "version": "2.0.0",
    "action": "recon",
   "bap_id": "staging-ondc.hamarajobs.ai",
    "bap_uri": "https://staging-ondc.hamarajobs.ai/bpp",
    "bpp_id": "sa_nocs.nbbl.com",
    "bpp_uri": "https://sa_nocs.nbbl.com/nocs_test",
    "transaction_id": "bf89da69-f803-4932-94d4-c688f503d94e",
    "message_id": "f4098f9c-6b44-4694-b463-a9f854c92148",
    "timestamp": "2025-02-20T08:41:51.897Z",
    "ttl": "P1D"
  },
  "message": {
      "orders": [{
        "settlements": [
          {
            "payment_id": "6a8a2f42-1344-40cb-a287-2b7ab39e2e91",
            "status": "PENDING",
            "amount": {
                "currency": "INR",
                "value": "0"
            },
            "commission": {
                "currency": "INR",
                "value": "0"
            },
            "withholding_amount": {
                "currency": "INR",
                "value": "0.00"
            },
            "tcs": {
                "currency": "INR",
                "value": "0.00"
            },
            "tds": {
                "currency": "INR",
                "value": "0.00"
            },
            "updated_at": "2025-02-19T18:38:19.386Z",
            "id": "cae6ea80-025c-4783-a67d-08df96845267"
          }
        ],
        "amount": {
					"currency": "INR",
					"value": "0"
				},
        "id": "6ba614bd-10db-4b8e-ad5d-d879b34d48ce"
      }
      ]
    }
    
}
